model/any_property_type.py
model/array_definition_type.py
model/array_property_type.py
model/boolean_property_type.py
model/collection_definition_type.py
model/collection_property_type.py
model/definition_type.py
model/generic_property_type.py
model/integer_property_type.py
model/map_definition_type.py
model/map_property_type.py
model/number_property_type.py
model/property_type.py
model/reference_property_type.py
model/scalar_property_type.py
model/string_property_type.py
model/struct_definition_type.py
model/type_schema.py
typeschema_model-3.0.1.dist-info/LICENSE
typeschema_model-3.0.1.dist-info/METADATA
typeschema_model-3.0.1.dist-info/WHEEL
typeschema_model-3.0.1.dist-info/top_level.txt
typeschema_model-3.0.1.dist-info/RECORD
